mooncake_mcp_mgme/__init__.py
mooncake_mcp_mgme-0.1.0.dist-info/METADATA
mooncake_mcp_mgme-0.1.0.dist-info/WHEEL
mooncake_mcp_mgme-0.1.0.dist-info/entry_points.txt
mooncake_mcp_mgme-0.1.0.dist-info/RECORD
