Metadata-Version: 2.4
Name: mooncake-mcp-mgme
Version: 0.1.0
Summary: Add your description here
Author-email: Lu Bu <bulu@microsoft.com>
Requires-Python: >=3.11
Requires-Dist: azure-identity>=1.23.0
Requires-Dist: azure-mgmt-resource>=23.4.0
Requires-Dist: mcp[cli]>=1.9.4
